<?xml version='1.0' encoding='UTF-8'?>    <marketplace>
        <node id="746" name="SlickEdit Core for Eclipse" url="http://marketplace.eclipse.org/content/slickedit-core-eclipse">
      <type>resource</type>
      <categories>
        <category id='6' name='Editor' url='http://marketplace.eclipse.org/taxonomy/term/6'/>
      </categories>
            
      <owner>jjones</owner>
      <favorited>1</favorited>
      <installstotal>0</installstotal>
      <installsrecent>0</installsrecent>
      <shortdescription><![CDATA[<p>SlickEdit Core is a subscription plug-in for Eclipse that allows developers to use the popular SlickEdit code editor as the default editor within the Eclipse environment. SlickEdit Core consists of the SlickEdit editor, 8 additional views, and the DIFFzilla differencing engine. </p>
<p>SlickEdit Core works with both Eclipse 3.5 and 3.4 and provides a wide range of advantages for the Eclipse developer including:</p>
<p>•	Eclipse Emulation<br />
•	System Verilog Language Support<br />
•	Vera Language Support<br />
•	Code Diff<br />
•	Overview Ruler<br />
•	D Language Support<br />
•	Export and Import Options<br />
•	Quick Start Configuration Wizard<br />
•	Symbol Coloring<br />
•	FTP Client View</p>
<p>“SlickEdit Core v3.5 includes many new features found in SlickEdit 2009 plus features unique to Core, including an Eclipse emulation and an overview ruler for the SlickEdit editor window,” said Scott Westfall, VP of Software Development. “Core's mixture of power, speed, and flexibility allows even the most accomplished developers to write code faster and more accurately &#8722; making it an indispensable plug-in for serious programmers.”</p>
<p>Pricing and Availability<br />
SlickEdit Core for Eclipse is available immediately as an annual subscription. Each subscription license is $99 per user per year and includes Maintenance and Support Service. For more information about SlickEdit and free trial downloads, please visit <a href="http://www.slickedit.com/products/slickedit-core/slickedit-core">http://www.slickedit.com/products/slickedit-core/slickedit-core</a> SlickEdit Core is a subscription plug-in for Eclipse that allows developers to use the popular SlickEdit code editor as the default editor within the Eclipse environment. SlickEdit Core consists of the SlickEdit editor, 8 additional views, and the DIFFzilla differencing engine. </p>
<p>SlickEdit Core works with both Eclipse 3.5 and 3.4 and provides a wide range of advantages for the Eclipse developer including:</p>
<p>•	Eclipse Emulation<br />
•	System Verilog Language Support<br />
•	Vera Language Support<br />
•	Code Diff<br />
•	Overview Ruler<br />
•	D Language Support<br />
•	Export and Import Options<br />
•	Quick Start Configuration Wizard<br />
•	Symbol Coloring<br />
•	FTP Client View</p>
<p>“SlickEdit Core v3.5 includes many new features found in SlickEdit 2009 plus features unique to Core, including an Eclipse emulation and an overview ruler for the SlickEdit editor window,” said Scott Westfall, VP of Software Development. “Core's mixture of power, speed, and flexibility allows even the most accomplished developers to write code faster and more accurately &#8722; making it an indispensable plug-in for serious programmers.”</p>
<p>Pricing and Availability<br />
SlickEdit Core for Eclipse is available immediately as an annual subscription. Each subscription license is $99 per user per year and includes Maintenance and Support Service. For more information about SlickEdit and free trial downloads, please visit <a href="http://www.slickedit.com/products/slickedit-core/slickedit-core">http://www.slickedit.com/products/slickedit-core/slickedit-core</a> </p>
]]></shortdescription>
      <body><![CDATA[<p>SlickEdit Core is a subscription plug-in for Eclipse that allows developers to use the popular SlickEdit code editor as the default editor within the Eclipse environment. SlickEdit Core consists of the SlickEdit editor, 8 additional views, and the DIFFzilla differencing engine. </p>
<p>SlickEdit Core works with both Eclipse 3.5 and 3.4 and provides a wide range of advantages for the Eclipse developer including:</p>
<p>•	Eclipse Emulation<br />
•	System Verilog Language Support<br />
•	Vera Language Support<br />
•	Code Diff<br />
•	Overview Ruler<br />
•	D Language Support<br />
•	Export and Import Options<br />
•	Quick Start Configuration Wizard<br />
•	Symbol Coloring<br />
•	FTP Client View</p>
<p>“SlickEdit Core v3.5 includes many new features found in SlickEdit 2009 plus features unique to Core, including an Eclipse emulation and an overview ruler for the SlickEdit editor window,” said Scott Westfall, VP of Software Development. “Core's mixture of power, speed, and flexibility allows even the most accomplished developers to write code faster and more accurately &#8722; making it an indispensable plug-in for serious programmers.”</p>
<p>Pricing and Availability<br />
SlickEdit Core for Eclipse is available immediately as an annual subscription. Each subscription license is $99 per user per year and includes Maintenance and Support Service. For more information about SlickEdit and free trial downloads, please visit <a href="http://www.slickedit.com/products/slickedit-core/slickedit-core">http://www.slickedit.com/products/slickedit-core/slickedit-core</a> SlickEdit Core is a subscription plug-in for Eclipse that allows developers to use the popular SlickEdit code editor as the default editor within the Eclipse environment. SlickEdit Core consists of the SlickEdit editor, 8 additional views, and the DIFFzilla differencing engine. </p>
<p>SlickEdit Core works with both Eclipse 3.5 and 3.4 and provides a wide range of advantages for the Eclipse developer including:</p>
<p>•	Eclipse Emulation<br />
•	System Verilog Language Support<br />
•	Vera Language Support<br />
•	Code Diff<br />
•	Overview Ruler<br />
•	D Language Support<br />
•	Export and Import Options<br />
•	Quick Start Configuration Wizard<br />
•	Symbol Coloring<br />
•	FTP Client View</p>
<p>“SlickEdit Core v3.5 includes many new features found in SlickEdit 2009 plus features unique to Core, including an Eclipse emulation and an overview ruler for the SlickEdit editor window,” said Scott Westfall, VP of Software Development. “Core's mixture of power, speed, and flexibility allows even the most accomplished developers to write code faster and more accurately &#8722; making it an indispensable plug-in for serious programmers.”</p>
<p>Pricing and Availability<br />
SlickEdit Core for Eclipse is available immediately as an annual subscription. Each subscription license is $99 per user per year and includes Maintenance and Support Service. For more information about SlickEdit and free trial downloads, please visit <a href="http://www.slickedit.com/products/slickedit-core/slickedit-core">http://www.slickedit.com/products/slickedit-core/slickedit-core</a> </p>
]]></body>
      <created>1218656913</created>
      <changed>1259943720</changed>
      <foundationmember>0</foundationmember>
      <homepageurl><![CDATA[http://www.slickedit.com/products/slickedit-core/slickedit-core]]></homepageurl>
      <image><![CDATA[http://www.slickedit.com/images/stories/core/core_box_new.gif]]></image>
      <version>3.5</version>
      <license>Commercial</license>
      <companyname><![CDATA[SlickEdit Inc.]]></companyname>
      <status>Production/Stable</status>
      <eclipseversion><![CDATA[3.4 & 3.5]]></eclipseversion>
      <supporturl><![CDATA[http://www.slickedit.com/support/]]></supporturl>
      <updateurl><![CDATA[http://www.slickedit.com/update/secore/galileoe ]]></updateurl>
    </node>
    </marketplace>
    