<?xml version='1.0' encoding='UTF-8'?>    <marketplace>
        <node id="70031" name="JavaElement View" url="http://marketplace.eclipse.org/content/javaelement-view">
      <type>resource</type>
      <categories>
        <category id='10' name='Languages' url='http://marketplace.eclipse.org/taxonomy/term/10'/>
        <category id='14' name='Source Code Analyzer' url='http://marketplace.eclipse.org/taxonomy/term/14'/>
        <category id='17' name='Tools' url='http://marketplace.eclipse.org/taxonomy/term/17'/>
        <category id='24' name='IDE' url='http://marketplace.eclipse.org/taxonomy/term/24'/>
        <category id='1966' name='Programming Languages' url='http://marketplace.eclipse.org/category/categories/programming-languages'/>
      </categories>
      <tags>
        <tag id='764' name='JDT' url='http://marketplace.eclipse.org/category/free-tagging/jdt'/>
      </tags>
      
      <owner>Deepak Azad</owner>
      <favorited>10</favorited>
      <installstotal>926</installstotal>
      <installsrecent>65</installsrecent>
      <shortdescription><![CDATA[<p>This plug-in from the Eclipse JDT UI team provides a view to visualize the Java elements in Eclipse's Java model. The view shows the result of many method calls on model elements either as children in the tree or as entries in the Properties view. A few operations on the elements are also available in the context menu and in the view menu.</p>
]]></shortdescription>
      <body><![CDATA[<p>This plug-in from the Eclipse JDT UI team provides a view to visualize the Java elements in Eclipse's Java model. The view shows the result of many method calls on model elements either as children in the tree or as entries in the Properties view. A few operations on the elements are also available in the context menu and in the view menu.</p>
]]></body>
      <created>1308804647</created>
      <changed>1308874696</changed>
      <foundationmember>1</foundationmember>
      <homepageurl><![CDATA[http://www.eclipse.org/jdt/ui/jeview/index.php]]></homepageurl>
      <image><![CDATA[http://marketplace.eclipse.org/sites/all/modules/custom/marketplace/images/no_image.png]]></image>
      <version></version>
      <license>EPL</license>
      <companyname><![CDATA[Eclipse JDT UI team]]></companyname>
      <status>Mature</status>
      <eclipseversion><![CDATA[3.3 and higher]]></eclipseversion>
      <supporturl><![CDATA[]]></supporturl>
      <updateurl><![CDATA[http://www.eclipse.org/jdt/ui/update-site]]></updateurl>
<ius>
<iu>org.eclipse.jdt.jeview.feature</iu>
</ius>
<platforms>
<platform>Windows</platform>
<platform>Mac</platform>
<platform>Linux/GTK</platform>
</platforms>
    </node>
    </marketplace>
    